kimai_python/__init__.py
kimai_python/api_client.py
kimai_python/configuration.py
kimai_python/rest.py
kimai_python/api/__init__.py
kimai_python/api/activity_api.py
kimai_python/api/customer_api.py
kimai_python/api/default_api.py
kimai_python/api/project_api.py
kimai_python/api/tag_api.py
kimai_python/api/team_api.py
kimai_python/api/timesheet_api.py
kimai_python/api/user_api.py
kimai_python/models/__init__.py
kimai_python/models/activity.py
kimai_python/models/activity_collection.py
kimai_python/models/activity_edit_form.py
kimai_python/models/activity_entity.py
kimai_python/models/activity_expanded.py
kimai_python/models/activity_meta.py
kimai_python/models/activity_meta_field.py
kimai_python/models/activity_rate.py
kimai_python/models/activity_rate_form.py
kimai_python/models/body.py
kimai_python/models/body1.py
kimai_python/models/body2.py
kimai_python/models/body3.py
kimai_python/models/body4.py
kimai_python/models/customer.py
kimai_python/models/customer2.py
kimai_python/models/customer_collection.py
kimai_python/models/customer_edit_form.py
kimai_python/models/customer_entity.py
kimai_python/models/customer_meta.py
kimai_python/models/customer_meta_field.py
kimai_python/models/customer_rate.py
kimai_python/models/customer_rate_form.py
kimai_python/models/i18n_config.py
kimai_python/models/project.py
kimai_python/models/project2.py
kimai_python/models/project_collection.py
kimai_python/models/project_edit_form.py
kimai_python/models/project_entity.py
kimai_python/models/project_expanded.py
kimai_python/models/project_meta.py
kimai_python/models/project_meta_field.py
kimai_python/models/project_rate.py
kimai_python/models/project_rate_form.py
kimai_python/models/tag_edit_form.py
kimai_python/models/tag_entity.py
kimai_python/models/team.py
kimai_python/models/team2.py
kimai_python/models/team3.py
kimai_python/models/team4.py
kimai_python/models/team5.py
kimai_python/models/team_collection.py
kimai_python/models/team_edit_form.py
kimai_python-0.2.9.dist-info/LICENSE
kimai_python-0.2.9.dist-info/METADATA
kimai_python-0.2.9.dist-info/WHEEL
kimai_python-0.2.9.dist-info/top_level.txt
kimai_python-0.2.9.dist-info/RECORD
